<Document ID="" Name="Page">
  <Data>
    <Section ID="1" Name="PageInfo" Type="STR">
      <Items Name="Page" Type="FIX">
        <Item Name="BookNo" Type="STR" Value="122" />
        <Item Name="PageNo" Type="STR" Value="59" />
        <Item Name="PageVersion" Type="STR" Value="1" />
        <Item Name="ImgUrl" Type="STR" Value="Active/Y2519/B0122/B0122_P0059_V01.jpg" />
        <Item Name="PageStatus" Type="STR" Value="Scan" />
        <Item Name="ScanDate" Type="STR" Value="31/6/2560 15:40:57" />
        <Item Name="ScanBy" Type="STR" Value="1" />
        <Item Name="DataEntryDate" Type="STR" Value="22/5/2560 18:11:16" />
        <Item Name="DataEntryBy" Type="STR" Value="Admin" />
        <Item Name="SummitDate" Type="STR" Value="24/5/2560 13:36:10" />
        <Item Name="SummitBy" Type="STR" Value="Admin" />
        <Item Name="ApproveDate" Type="STR" Value="25/5/2560 15:38:40" />
        <Item Name="ApproveBy" Type="STR" Value="Admin" />
        <Item Name="CreateDate" Type="STR" Value="18/5/2560 18:0:51" />
        <Item Name="CreateBy" Type="STR" Value="Admin" />
        <Item Name="UpdateDate" Type="STR" Value="31/6/2560 15:40:57" />
        <Item Name="UpdateBy" Type="STR" Value="1" />
      </Items>
    </Section>
    <Section ID="2" Name="Record" Type="STR">
      <Items Name="RecordInfo" Type="SEQ">
        <Means Name="Record">
          <Mean ID="C00" Name="GunRegID" Type="STR" Desc="ทะเบียนปืน" />
          <Mean ID="C01" Name="GunNo" Type="STR" Desc="เลขหมายปืน" />
          <Mean ID="C02" Name="GunGroup" Type="STR" Desc="สั้น/ยาว" />
          <Mean ID="C03" Name="GunType" Type="STR" Desc="ชนิดอาวุธปืน" />
          <Mean ID="C04" Name="GunSize" Type="STR" Desc="ขนาด" />
          <Mean ID="C05" Name="GunBrand" Type="STR" Desc="ยี่ห้อ" />
          <Mean ID="C06" Name="GunMaxShot" Type="STR" Desc="บรรจุ(นัด)" />
          <Mean ID="C07" Name="GunBarrel" Type="STR" Desc="ความยาวลำกล้อง" />
          <Mean ID="C08" Name="GunColor" Type="STR" Desc="สีปืน" />
          <Mean ID="C09" Name="GunOwner" Type="STR" Desc="เจ้าของปืน" />
          <Mean ID="C10" Name="GunLottotal" Type="STR" Desc="จำนวน" />
          <Mean ID="C11" Name="GunRemark" Type="STR" Desc="หมายเหตุ" />
          <Mean ID="C12" Name="GunRegDate" Type="STR" Desc="วันที่ลงทะเบียน" />
          <Mean ID="C13" Name="GunCountry" Type="STR" Desc="ประเทศนำเข้า" />
          <Mean ID="C14" Name="CreateDate" Type="STR" Desc="" />
          <Mean ID="C15" Name="CreateBy" Type="STR" Desc="" />
          <Mean ID="C16" Name="UpdateDate" Type="STR" Desc="" />
          <Mean ID="C17" Name="UpdateBy" Type="STR" Desc="" />
        </Means>
        <Item C00="51161" C01="D573554" C02="" C03="เดี่ยวลูกซอง" C04="12" C05="สตีเว่นส์" C06="" C07="" C08="" C09="นางฉายภมร วัฒนะโชติ" C10="25" C11="2783, ปว ที่ 276/23 ลงวันที่ 8 ม.ค. 23" C12="15/01/2524" C13="อเมริกา" C14="22/5/2560  18:2:4" C15="Admin" C16="25/5/2560  15:38:50" C17="Admin" />
        <Item C00="51162" C01="D573557" C02="" C03="เดี่ยวลูกซอง" C04="12" C05="สตีเว่นส์" C06="" C07="" C08="" C09="นางฉายภมร วัฒนะโชติ" C10="25" C11="2783, ปว ที่ 276/23 ลงวันที่ 8 ม.ค. 23" C12="15/01/2524" C13="อเมริกา" C14="22/5/2560  18:2:4" C15="Admin" C16="25/5/2560  15:38:50" C17="Admin" />
        <Item C00="51163" C01="D573552" C02="" C03="เดี่ยวลูกซอง" C04="12" C05="สตีเว่นส์" C06="" C07="" C08="" C09="นางฉายภมร วัฒนะโชติ" C10="25" C11="2783, ปว ที่ 276/23 ลงวันที่ 8 ม.ค. 23" C12="15/01/2524" C13="อเมริกา" C14="22/5/2560  18:2:4" C15="Admin" C16="25/5/2560  15:38:50" C17="Admin" />
        <Item C00="51164" C01="D573553" C02="" C03="เดี่ยวลูกซอง" C04="12" C05="สตีเว่นส์" C06="" C07="" C08="" C09="นางฉายภมร วัฒนะโชติ" C10="25" C11="2783, ปว ที่ 276/23 ลงวันที่ 8 ม.ค. 23" C12="15/01/2524" C13="อเมริกา" C14="22/5/2560  18:2:4" C15="Admin" C16="25/5/2560  15:38:50" C17="Admin" />
        <Item C00="51165" C01="D573558" C02="" C03="เดี่ยวลูกซอง" C04="12" C05="สตีเว่นส์" C06="" C07="" C08="" C09="นางฉายภมร วัฒนะโชติ" C10="25" C11="2783, ปว ที่ 276/23 ลงวันที่ 8 ม.ค. 23" C12="15/01/2524" C13="อเมริกา" C14="22/5/2560  18:2:4" C15="Admin" C16="25/5/2560  15:38:50" C17="Admin" />
        <Item C00="51166" C01="D573645" C02="" C03="เดี่ยวลูกซอง" C04="12" C05="สตีเว่นส์" C06="" C07="" C08="" C09="นางฉายภมร วัฒนะโชติ" C10="25" C11="2783, ปว ที่ 276/23 ลงวันที่ 8 ม.ค. 23" C12="15/01/2524" C13="อเมริกา" C14="22/5/2560  18:2:4" C15="Admin" C16="25/5/2560  15:38:50" C17="Admin" />
        <Item C00="51167" C01="D573642" C02="" C03="เดี่ยวลูกซอง" C04="12" C05="สตีเว่นส์" C06="" C07="" C08="" C09="นางฉายภมร วัฒนะโชติ" C10="25" C11="2783, ปว ที่ 276/23 ลงวันที่ 8 ม.ค. 23" C12="15/01/2524" C13="อเมริกา" C14="22/5/2560  18:2:4" C15="Admin" C16="25/5/2560  15:38:50" C17="Admin" />
        <Item C00="51168" C01="D573649" C02="" C03="เดี่ยวลูกซอง" C04="12" C05="สตีเว่นส์" C06="" C07="" C08="" C09="นางฉายภมร วัฒนะโชติ" C10="25" C11="2783, ปว ที่ 276/23 ลงวันที่ 8 ม.ค. 23" C12="15/01/2524" C13="อเมริกา" C14="22/5/2560  18:2:4" C15="Admin" C16="25/5/2560  15:38:50" C17="Admin" />
        <Item C00="51169" C01="D573648" C02="" C03="เดี่ยวลูกซอง" C04="12" C05="สตีเว่นส์" C06="" C07="" C08="" C09="นางฉายภมร วัฒนะโชติ" C10="25" C11="2783, ปว ที่ 276/23 ลงวันที่ 8 ม.ค. 23" C12="15/01/2524" C13="อเมริกา" C14="22/5/2560  18:2:4" C15="Admin" C16="25/5/2560  15:38:50" C17="Admin" />
        <Item C00="51170" C01="D573650" C02="" C03="เดี่ยวลูกซอง" C04="12" C05="สตีเว่นส์" C06="" C07="" C08="" C09="นางฉายภมร วัฒนะโชติ" C10="25" C11="2783, ปว ที่ 276/23 ลงวันที่ 8 ม.ค. 23" C12="15/01/2524" C13="อเมริกา" C14="22/5/2560  18:2:4" C15="Admin" C16="25/5/2560  15:38:50" C17="Admin" />
        <Item C00="51172" C01="D573641" C02="" C03="เดี่ยวลูกซอง" C04="12" C05="สตีเว่นส์" C06="" C07="" C08="" C09="นางฉายภมร วัฒนะโชติ" C10="25" C11="2783, ปว ที่ 276/23 ลงวันที่ 8 ม.ค. 23" C12="15/01/2524" C13="อเมริกา" C14="22/5/2560  18:2:4" C15="Admin" C16="25/5/2560  15:38:50" C17="Admin" />
        <Item C00="51173" C01="D573643" C02="" C03="เดี่ยวลูกซอง" C04="12" C05="สตีเว่นส์" C06="" C07="" C08="" C09="นางฉายภมร วัฒนะโชติ" C10="25" C11="2783, ปว ที่ 276/23 ลงวันที่ 8 ม.ค. 23" C12="15/01/2524" C13="อเมริกา" C14="22/5/2560  18:2:4" C15="Admin" C16="25/5/2560  15:38:50" C17="Admin" />
        <Item C00="51174" C01="D573647" C02="" C03="เดี่ยวลูกซอง" C04="12" C05="สตีเว่นส์" C06="" C07="" C08="" C09="นางฉายภมร วัฒนะโชติ" C10="25" C11="2783, ปว ที่ 276/23 ลงวันที่ 8 ม.ค. 23" C12="15/01/2524" C13="อเมริกา" C14="22/5/2560  18:2:4" C15="Admin" C16="25/5/2560  15:38:50" C17="Admin" />
        <Item C00="51175" C01="D573644" C02="" C03="เดี่ยวลูกซอง" C04="12" C05="สตีเว่นส์" C06="" C07="" C08="" C09="นางฉายภมร วัฒนะโชติ" C10="25" C11="2783, ปว ที่ 276/23 ลงวันที่ 8 ม.ค. 23" C12="15/01/2524" C13="อเมริกา" C14="22/5/2560  18:2:4" C15="Admin" C16="25/5/2560  15:38:50" C17="Admin" />
        <Item C00="51176" C01="D573551" C02="" C03="เดี่ยวลูกซอง" C04="12" C05="สตีเว่นส์" C06="" C07="" C08="" C09="นางฉายภมร วัฒนะโชติ" C10="25" C11="2783, ปว ที่ 276/23 ลงวันที่ 8 ม.ค. 23" C12="15/01/2524" C13="อเมริกา" C14="22/5/2560  18:2:4" C15="Admin" C16="25/5/2560  15:38:50" C17="Admin" />
        <Item C00="51177" C01="D573560" C02="" C03="เดี่ยวลูกซอง" C04="12" C05="สตีเว่นส์" C06="" C07="" C08="" C09="นางฉายภมร วัฒนะโชติ" C10="25" C11="2783, ปว ที่ 276/23 ลงวันที่ 8 ม.ค. 23" C12="15/01/2524" C13="อเมริกา" C14="22/5/2560  18:2:4" C15="Admin" C16="25/5/2560  15:38:50" C17="Admin" />
        <Item C00="51178" C01="D573556" C02="" C03="เดี่ยวลูกซอง" C04="12" C05="สตีเว่นส์" C06="" C07="" C08="" C09="นางฉายภมร วัฒนะโชติ" C10="25" C11="2783, ปว ที่ 276/23 ลงวันที่ 8 ม.ค. 23" C12="15/01/2524" C13="อเมริกา" C14="22/5/2560  18:2:4" C15="Admin" C16="25/5/2560  15:38:50" C17="Admin" />
        <Item C00="51179" C01="D573565" C02="" C03="เดี่ยวลูกซอง" C04="12" C05="สตีเว่นส์" C06="" C07="" C08="" C09="นางฉายภมร วัฒนะโชติ" C10="25" C11="2783, ปว ที่ 276/23 ลงวันที่ 8 ม.ค. 23" C12="15/01/2524" C13="อเมริกา" C14="22/5/2560  18:2:4" C15="Admin" C16="25/5/2560  15:38:50" C17="Admin" />
        <Item C00="51180" C01="D573561" C02="" C03="เดี่ยวลูกซอง" C04="12" C05="สตีเว่นส์" C06="" C07="" C08="" C09="นางฉายภมร วัฒนะโชติ" C10="25" C11="2783, ปว ที่ 276/23 ลงวันที่ 8 ม.ค. 23" C12="15/01/2524" C13="อเมริกา" C14="22/5/2560  18:2:4" C15="Admin" C16="25/5/2560  15:38:50" C17="Admin" />
      </Items>
    </Section>
  </Data>
</Document>