<Document ID="" Name="">
  <Data>
    <Section ID="1" Name="GunBookInfo" Type="STR">
      <Items Name="GunBook" Type="FIX">
        <Item Name="BookNo" Type="STR" Value="491" />
        <Item Name="BookVersion" Type="STR" Value="" />
        <Item Name="BookYear" Type="STR" Value="2558" />
        <Item Name="GunRegIDPrefix" Type="STR" Value="กท" />
        <Item Name="GunRegIDStart" Type="STR" Value="58200001" />
        <Item Name="GunRegIDEnd" Type="STR" Value="58205920" />
        <Item Name="PageTotal" Type="STR" Value="400" />
        <Item Name="BookStatus" Type="STR" Value="Create" />
        <Item Name="CreateDate" Type="STR" Value="14/10/2560 2:6:0" />
        <Item Name="CreateBy" Type="STR" Value="Admin" />
        <Item Name="UpdateDate" Type="STR" Value="28/3/2561 9:38:15" />
        <Item Name="UpdateBy" Type="STR" Value="Admin" />
        <Item Name="Expire_Date" Type="STR" Value="" />
        <Item Name="destrory_date" Type="STR" Value="" />
      </Items>
    </Section>
  </Data>
</Document>